szn_pyfastrpc/__init__.py
szn_pyfastrpc/autostart.py
szn_pyfastrpc/main.py
szn_pyfastrpc/open_readme.py
szn_pyfastrpc/parser.py
szn_pyfastrpc/protocol.py
szn_pyfastrpc/readme_handler.py
szn_pyfastrpc/serializer.py
szn_pyfastrpc/utils.py
szn_pyfastrpc-1.2.5.dist-info/licenses/LICENSE
szn_pyfastrpc-1.2.5.dist-info/METADATA
szn_pyfastrpc-1.2.5.dist-info/WHEEL
szn_pyfastrpc-1.2.5.dist-info/entry_points.txt
szn_pyfastrpc-1.2.5.dist-info/top_level.txt
szn_pyfastrpc-1.2.5.dist-info/RECORD
