Metadata-Version: 2.4
Name: szn-pyfastrpc
Version: 1.2.5
Summary: A FastRPC protocol implementation in Python
Home-page: https://github.com/opicevopice/szn-pyfastrpc
Author: Roman Skvara
Author-email: skvara.roman@gmail.com
License: MIT
Classifier: Programming Language :: Python :: 3
Classifier: License :: OSI Approved :: MIT License
License-File: LICENSE
Requires-Dist: requests-html>=0.10.0
Dynamic: author
Dynamic: author-email
Dynamic: classifier
Dynamic: description
Dynamic: description-content-type
Dynamic: home-page
Dynamic: license
Dynamic: license-file
Dynamic: requires-dist
Dynamic: summary
